sapiens_inference/__init__.py
sapiens_inference/common.py
sapiens_inference/depth.py
sapiens_inference/detector.py
sapiens_inference/normal.py
sapiens_inference/predictor.py
sapiens_inference/segmentation.py
sapiens_inferece-0.2.0.dist-info/LICENSE
sapiens_inferece-0.2.0.dist-info/METADATA
sapiens_inferece-0.2.0.dist-info/WHEEL
sapiens_inferece-0.2.0.dist-info/top_level.txt
sapiens_inferece-0.2.0.dist-info/RECORD
