Metadata-Version: 2.1
Name: sapiens-inferece
Version: 0.2.0
Summary: Run Sapiens Human Foundation models in Pytorch
Author: Ibai Gorordo
License: MIT
Project-URL: Homepage, https://github.com/ibaiGorordo/Sapiens-Pytorch-Inference
Keywords: deep-learning,computer-vision,Segmentation,Human Foundation,Normal-Estimation,Pose-Estimation,Depth-Estimation
License-File: LICENSE
Requires-Dist: torch
Requires-Dist: opencv-python
Requires-Dist: torchvision
Requires-Dist: huggingface-hub
Provides-Extra: export
Requires-Dist: onnx; extra == "export"
Requires-Dist: onnxruntime; extra == "export"
